ansimagic/__init__.py
ansimagic/brush.py
ansimagic/clear.py
ansimagic/cursor.py
ansimagic/presets.py
ansimagic/tools.py
ansimagic-0.4.1.dist-info/METADATA
ansimagic-0.4.1.dist-info/WHEEL
ansimagic-0.4.1.dist-info/top_level.txt
ansimagic-0.4.1.dist-info/RECORD
